eschergraph/__init__.py
eschergraph/agents/__init__.py
eschergraph/agents/agent.py
eschergraph/agents/embedding.py
eschergraph/agents/jinja_helper.py
eschergraph/agents/llm.py
eschergraph/agents/prompts/community_prompt.jinja
eschergraph/agents/prompts/identifying_nodes.jinja
eschergraph/agents/prompts/json_build.jinja
eschergraph/agents/prompts/json_figure.jinja
eschergraph/agents/prompts/json_keywords.jinja
eschergraph/agents/prompts/json_property.jinja
eschergraph/agents/prompts/json_table.jinja
eschergraph/agents/prompts/search/global_search_context.jinja
eschergraph/agents/prompts/search/question_with_context.jinja
eschergraph/agents/protocols.py
eschergraph/agents/providers/__init__.py
eschergraph/agents/providers/jina.py
eschergraph/agents/providers/openai.py
eschergraph/agents/reranker.py
eschergraph/agents/tools.py
eschergraph/benchmarking/__init__.py
eschergraph/builder/__init__.py
eschergraph/builder/build_log.py
eschergraph/builder/build_pipeline.py
eschergraph/builder/building_tools.py
eschergraph/builder/reader/fast_pdf_parser/__init__.py
eschergraph/builder/reader/fast_pdf_parser/models.py
eschergraph/builder/reader/fast_pdf_parser/parser.py
eschergraph/builder/reader/multi_modal/data_structure.py
eschergraph/builder/reader/multi_modal/multi_modal_parser.py
eschergraph/builder/reader/pdf_document_layout_analysis/__init__.py
eschergraph/builder/reader/pdf_document_layout_analysis/fast_trainer/__init__.py
eschergraph/builder/reader/pdf_document_layout_analysis/fast_trainer/model_configuration.py
eschergraph/builder/reader/pdf_document_layout_analysis/fast_trainer/paragraph.py
eschergraph/builder/reader/pdf_document_layout_analysis/fast_trainer/paragraph_extractor_trainer.py
eschergraph/builder/reader/pdf_document_layout_analysis/pdf_features/__init__.py
eschergraph/builder/reader/pdf_document_layout_analysis/pdf_features/pdf_features.py
eschergraph/builder/reader/pdf_document_layout_analysis/pdf_features/pdf_font.py
eschergraph-0.3.1.dist-info/LICENSE
eschergraph-0.3.1.dist-info/METADATA
eschergraph-0.3.1.dist-info/WHEEL
eschergraph-0.3.1.dist-info/RECORD
